{
  "schema_system_version": "vp_schema_v1",
  "schema_version": "detalize_face_npz_v1",
  "producer": "detalize_face",
  "artifact_kind": "npz",
  "allow_extra_keys": false,
  "meta": {
    "required_keys": [
      "producer",
      "producer_version",
      "schema_version",
      "created_at",
      "platform_id",
      "video_id",
      "run_id",
      "config_hash",
      "sampling_policy_version",
      "dataprocessor_version",
      "status",
      "empty_reason",
      "models_used",
      "model_signature",
      "stage_timings_ms"
    ],
    "optional_keys": [
      "total_frames",
      "processed_frames",
      "frames_dir",
      "analysis_fps",
      "analysis_width",
      "analysis_height",
      "ui_payload",
      "module_sampling_policy_version"
    ]
  },
  "fields": {
    "frame_indices": { "required": true, "tier": "model_facing", "dtype": "int32", "shape": ["N"] },
    "times_s": { "required": true, "tier": "model_facing", "dtype": "float32", "shape": ["N"] },
    "face_count": { "required": true, "tier": "model_facing", "dtype": "float32", "shape": ["N"] },
    "primary_gaze_at_camera_prob": { "required": true, "tier": "model_facing", "dtype": "float32", "shape": ["N"] },
    "primary_blink_rate": { "required": true, "tier": "model_facing", "dtype": "float32", "shape": ["N"] },
    "primary_attention_score": { "required": true, "tier": "model_facing", "dtype": "float32", "shape": ["N"] },
    "primary_quality_proxy_score": { "required": true, "tier": "model_facing", "dtype": "float32", "shape": ["N"] },
    "primary_face_sharpness": { "required": true, "tier": "model_facing", "dtype": "float32", "shape": ["N"] },
    "primary_occlusion_proxy": { "required": true, "tier": "model_facing", "dtype": "float32", "shape": ["N"] },
    "primary_speech_activity_prob": { "required": true, "tier": "model_facing", "dtype": "float32", "shape": ["N"] },
    "faces_agg": { "required": true, "tier": "analytics", "dtype": "object", "shape": [] },
    "summary": { "required": true, "tier": "analytics", "dtype": "object", "shape": [] }
  }
}


